homework_4/hdl/q5/src/moore_1011.sv
module moore_1011 (
	input  logic clk,
	input  logic rst_n,
	input  logic j,
	output logic w
);
    
	logic [2:0] next_state, present_state;

	always_comb begin
		next_state = 3'b000;
		case(present_state)
			3'b000: next_state = j ? 3'b001 : 3'b000;
			3'b001: next_state = j ? 3'b001 : 3'b010;
			3'b010: next_state = j ? 3'b011 : 3'b000;
			3'b011: next_state = j ? 3'b100 : 3'b010;
			3'b100: next_state = j ? 3'b001 : 3'b010;
			default: next_state = 3'b000;
		endcase
	end

	assign w = (present_state == 3'b100) ? 1'b1 : 1'b0;

	always_ff @(posedge clk or negedge rst_n) begin
		if (!rst_n) 
			present_state <= 3'b000;
		else
			present_state <= next_state;
	end
    
endmodule

homework_4/hdl/q5/sim/tb_moore_1011.sv
//-------------------------------------------------------------------------------------------------
//
//  File: tb_moore_1011.sv
//  Description: Assertion based testbench for Moore sequence detector (1011).
//
//  Author:
//      - A. Pedersen
//
//-------------------------------------------------------------------------------------------------

`timescale 1ns / 1ps

module tb_moore_1011 ();

  logic clk;
  logic rst_n;
  logic j;
  logic w;
  int seed = 12345;

  moore_1011 dut (
    .clk    ( clk   ),
    .rst_n  ( rst_n ),
    .j      ( j     ),
    .w      ( w     )
  );

  initial clk = 0;
  always #5 clk = ~clk;

  // stimulus
  initial begin
    $dumpfile("tb_moore_1011.vcd");
    $dumpvars(0, tb_moore_1011);
    rst_n = 0;
    j     = 0;
    repeat (2) @(posedge clk);
    rst_n = 1;

    // sequence
    j <= 1; @(posedge clk);
    j <= 0; @(posedge clk);
    j <= 1; @(posedge clk);
    j <= 1; @(posedge clk);

    // random values after
    repeat (10) begin
      j <= $random(seed) % 2;
      @(posedge clk);
    end

    $display("[%0t] Testbench done.", $time);
    $finish;
  end

  // store last 4 input bits
  logic [3:0] last_4;
  always_ff @(posedge clk or negedge rst_n) begin
    if (!rst_n)
      last_4 <= 4'b0000;
    else
      last_4 <= {last_4[2:0], j};
  end

  // whenever w is high, the last four input bits are equal 1011
  property p_correct_seq;
    @(posedge clk) disable iff(!rst_n)
    w |-> (last_4 == 4'b1011);
  endproperty

  // w should only be high for one cycle
  property p_w_one_cycle;
    @(posedge clk) disable iff(!rst_n)
    w |=> !w;
  endproperty

  a_correct_seq: assert property (p_correct_seq)
    else $error("[%0t] Error: w is high but input sequence is not 1011", $time);

  a_w_one_cycle: assert property (p_w_one_cycle)
    else $error("[%0t] Error: w was high for more than one cycle", $time);

endmodule

homework_4/waveforms/tb_moore_1011.vcd
$date
   Sun Oct 19 11:20:33 2025
$end

$version
  2024.2.0
  $dumpfile ("tb_moore_1011.vcd") 
$end

$timescale
  1ps
$end

$scope module tb_moore_1011 $end
$var reg 1 ! clk $end
$var reg 1 " rst_n $end
$var reg 1 # j $end
$var reg 1 $ w $end
$var reg 32 % seed [31:0] $end
$var reg 4 & last_4 [3:0] $end
$scope module dut $end
$var wire 1 ' clk $end
$var wire 1 ( rst_n $end
$var wire 1 ) j $end
$var reg 1 $ w $end
$var reg 3 * next_state [2:0] $end
$var reg 3 + present_state [2:0] $end
$upscope $end
$upscope $end
$enddefinitions $end

#0
$dumpvars
0!
0"
0#
0$
b11000000111001 %
b0 &
0'
0(
0)
b0 *
b0 +
$end

#5000
1!
1'

#10000
0!
0'

#15000
1!
1"
1#
1'
1(
1)
b1 *

#20000
0!
0'

#25000
1!
0#
b1 &
1'
0)
b10 *
b1 +

#30000
0!
0'

#35000
1!
1#
b10 &
1'
1)
b11 *
b10 +

#40000
0!
0'

#45000
1!
b101 &
1'
b100 *
b11 +

#50000
0!
0'

#55000
1!
1$
b1011 &
1'
b1 *
b100 +

#60000
0!
0'

#65000
1!
0$
b111 &
1'
b1 *
b1 +

#70000
0!
0'

#75000
1!
0#
b1111 &
1'
0)
b10 *

#80000
0!
0'

#85000
1!
b1110 &
1'
b0 *
b10 +

#90000
0!
0'

#95000
1!
1#
b1100 &
1'
1)
b1 *
b0 +

#100000
0!
0'

#105000
1!
b1001 &
1'
b1 *
b1 +

#110000
0!
0'

#115000
1!
b11 &
1'

#120000
0!
0'

#125000
1!
b111 &
1'

#130000
0!
0'

#135000
1!
b1111 &
1'

#140000
0!
0'

#145000
1!
0#
1'
0)
b10 *

