milestone_1/hdl/src/fulladder.sv
//-------------------------------------------------------------------------------------------------
//
//  File: fulladder.sv
//
//  Author:
//      - A. Pedersen
//      - J. Sadiq
//      - J. Yang
//
//-------------------------------------------------------------------------------------------------

//  fulladder fa_0 (
//    .a(),
//    .b(),
//    .c_in(),
//    .sum(),
//    .c_out()
//  );

module fulladder (
    input   logic a_i,
    input   logic b_i,
    input   logic c_i,
    output  logic sum_o,
    output  logic c_o
  );

  assign sum_o  = a_i ^ b_i ^ c_i;
  assign c_o    = (a_i & b_i) | (a_i & c_i) | (b_i & c_i);

endmodule

milestone_1/hdl/src/cl_subtractor.sv
//-------------------------------------------------------------------------------------------------
//
//  File: cl_subtractor.sv
//  Description: Carry lookahead subtractor using a cascade of full adders and additional logic
//
//  Author:
//      - A. Pedersen
//      - J. Sadiq
//      - J. Yang
//
//  References:
//    - https://nandland.com/carry-lookahead-adder/
//
//-------------------------------------------------------------------------------------------------

//  cl_subtractor #(
//    .Width(8)
//  ) dut (
//    .a_i(),
//    .b_i(),
//    .sub_i(),
//    .sum_o(),
//    .c_o()
//  );

module cl_subtractor #(
    parameter Width = 8
  ) (
    input   logic [Width-1:0] a_i,
    input   logic [Width-1:0] b_i,
    input   logic             sub_i,
    output  logic [Width-1:0] sum_o,
    output  logic             c_o
  );

  logic [Width-1:0] w_G; // Generate terms: Gi = Ai * Bi
  logic [Width-1:0] w_P; // Propagate terms: Pi = Ai + Bi
  logic [Width-1:0] w_S; // Sum
  logic [Width:0]   w_C; // Carry terms
  assign w_C[0] = sub_i;

  genvar i;
  generate
    for (i = 0; i < Width; i++) begin : adder_chain
      fulladder fa (
        .a_i      (a_i[i]),
        .b_i      (b_i[i] ^ sub_i),
        .c_i      (w_C[i]),
        .sum_o    (w_S[i]),
        .c_o  ()
      );

      assign w_G[i] = a_i[i] & b_i[i];
      assign w_P[i] = a_i[i] | b_i[i];

      // CLA terms: Ci+1 = Gi + Pi*Ci
      if (i < Width) begin : gen_cla_terms
        assign w_C[i+1] = w_G[i] | (w_P[i] & w_C[i]);
      end
    end
  endgenerate

  assign sum_o = w_S;
  assign c_o = w_C[Width];

endmodule

milestone_4/hdl/src/mux.sv
//-------------------------------------------------------------------------------------------------
//
//  File: mux.sv
//  Description: Parameterized NX-to-X multiplexer module.
//
//  Author(s):
//      - A. Pedersen
//      - J. Sadiq
//      - J. Yang
//
//-------------------------------------------------------------------------------------------------

//  mux #(
//    .Bitwidth(),
//    .N()
//   ) mux_0 (
//    .d_i(),
//    .sel_i(),
//    .d_o()
//  );

module mux #(
    parameter   BitWidth  = 8,
    parameter   N         = 8,
    localparam  SelWidth  = $clog2(N)
  ) (
    input  logic [BitWidth-1:0] d_i [N-1:0],
    input  logic [SelWidth-1:0] sel_i,
    output logic [BitWidth-1:0] d_o
  );

  assign d_o = d_i[sel_i];

endmodule

milestone_1/hdl/src/alu.sv
//-------------------------------------------------------------------------------------------------
//
//  File: alu.sv
//  Description:
//
//  Author(s):
//      - A. Pedersen
//      - J. Sadiq
//      - J. Yang
//
//-------------------------------------------------------------------------------------------------

//  alu alu_0 #(
//    .BW(8)
//  ) (
//    .in_a(),
//    .in_b(),
//    .opcode(),
//    .out(),
//    .flags()
//  );

module alu #(
    parameter BW = 8
  ) (
    input   logic signed  [BW-1:0]  in_a,   // Operand A
    input   logic signed  [BW-1:0]  in_b,   // Operand B
    input   logic         [2:0]     opcode, // Operation code
    output  logic signed  [BW-1:0]  out,    // Output result
    output  logic signed  [2:0]     flags   // Flags of the result
  );

  logic flag_overflow;
  logic flag_negative;
  logic flag_zero;

  // instantiate signals for all possible outputs
  logic [BW-1:0] out_adder;
  logic [BW-1:0] out_and;
  logic [BW-1:0] out_or;
  logic [BW-1:0] out_xor;
  logic [BW-1:0] out_mova;
  logic [BW-1:0] out_movb;

  // route selected op to the output
  mux #(
    .BitWidth(BW),
    .N(8)
  ) output_mux (
    .d_i({out_movb, out_mova, out_adder, out_xor, out_or, out_and, out_adder, out_adder}),
    .sel_i(opcode),
    .d_o(out)
  );

  // op: addition, subtraction, and increment
  cl_subtractor #(
    .Width(BW)
  ) cl_subtractor_0 (
    .a_i    ( in_a                        ),
    .b_i    ( opcode == 5 ? BW'(1) : in_b ),
    .sub_i  ( opcode == 1 ? 1'b1   : 1'b0 ),
    .sum_o  ( out_adder                   ),
    .c_o    ()
  );

  // op: bitwise and
  assign out_and  = in_a & in_b;

  // op: bitiwse or
  assign out_or   = in_a | in_b;

  // op: bitwise xor
  assign out_xor  = in_a ^ in_b;

  // op: passthrough of a
  assign out_mova = in_a;

  // op: passthrough of b
  assign out_movb = in_b;

  // flag generation
  always_comb begin : check_overflow
    flag_overflow = 1'b0;
    if (opcode == 3'b000 || opcode == 3'b001 | opcode == 3'b101) begin
      flag_overflow  = (in_a[BW-1] == in_b[BW-1]) && (in_a[BW-1] != out_adder[BW-1]);
    end
  end

  assign flag_negative  = out[BW-1];
  assign flag_zero      = (out == '0);

  assign flags = {flag_overflow, flag_negative, flag_zero};

endmodule

milestone_1/hdl/src/top.sv
//-------------------------------------------------------------------------------------------------
//
//  File: top.sv
//  Description: top module for testbench
//
//  Author:
//      - A. Pedersen
//      - J. Sadiq
//      - J. Yang
//
//-------------------------------------------------------------------------------------------------

module top
  (
    input   logic [7:0] a,
    input   logic [7:0] b,
    input   logic [2:0] opcode,
    output  logic [7:0] out,
    output  logic [2:0] flags
  );

    // DUT instance
    alu #(
      .BW(8)
    ) alu_0 (
      .in_a(a),
      .in_b(b),
      .opcode(opcode),
      .out(out),
      .flags(flags)
    );

    // Stimulus
    initial begin

      if ($test$plusargs("trace") != 0) begin
        $dumpfile("logs/vlt_dump.vcd");
        $dumpvars();
      end

      $display("[%0t] Starting simulation...", $time);
    end

endmodule

/* Top module for Urbana board
module top
  (
    input   logic [15:0] SW,
    output  logic [15:0] LED
  );

    logic [5:0] a;
    logic [5:0] b;
    logic [2:0] op;
    logic [5:0] out;
    logic [2:0] flags;
    
    assign a      = SW[5:0];
    assign b      = SW[11:6];
    assign op     = SW[14:12];
    assign out    = LED[5:0];
    assign flags  = LED[15:13];

    // ALU instance
    alu #(
      .BW(6)
    ) alu_0 (
      .in_a(a),
      .in_b(b),
      .opcode(op),
      .out(out),
      .flags(flags)
    );

endmodule
*/

presentation/waveforms/alu.vcd
$version Generated by VerilatedVcd $end
$timescale 1ps $end
 $scope module TOP $end
  $var wire 8 M a [7:0] $end
  $var wire 8 N b [7:0] $end
  $var wire 3 O opcode [2:0] $end
  $var wire 8 P out [7:0] $end
  $var wire 3 Q flags [2:0] $end
  $scope module top $end
   $var wire 8 M a [7:0] $end
   $var wire 8 N b [7:0] $end
   $var wire 3 O opcode [2:0] $end
   $var wire 8 P out [7:0] $end
   $var wire 3 Q flags [2:0] $end
   $scope module alu_0 $end
    $var wire 32 d BW [31:0] $end
    $var wire 8 M in_a [7:0] $end
    $var wire 8 N in_b [7:0] $end
    $var wire 3 O opcode [2:0] $end
    $var wire 8 P out [7:0] $end
    $var wire 3 Q flags [2:0] $end
    $var wire 1 # flag_overflow $end
    $var wire 1 $ flag_negative $end
    $var wire 1 % flag_zero $end
    $var wire 8 & out_adder [7:0] $end
    $var wire 8 ' out_and [7:0] $end
    $var wire 8 ( out_or [7:0] $end
    $var wire 8 ) out_xor [7:0] $end
    $var wire 8 M out_mova [7:0] $end
    $var wire 8 N out_movb [7:0] $end
    $scope module cl_subtractor_0 $end
     $var wire 32 d Width [31:0] $end
     $var wire 8 M a_i [7:0] $end
     $var wire 8 * b_i [7:0] $end
     $var wire 1 R sub_i $end
     $var wire 8 & sum_o [7:0] $end
     $var wire 1 + c_o $end
     $var wire 8 , w_G [7:0] $end
     $var wire 8 - w_P [7:0] $end
     $var wire 8 & w_S [7:0] $end
     $var wire 9 S w_C [8:0] $end
     $scope module adder_chain[0] $end
      $scope module fa $end
       $var wire 1 T a_i $end
       $var wire 1 . b_i $end
       $var wire 1 R c_i $end
       $var wire 1 / sum_o $end
       $var wire 1 U c_o $end
      $upscope $end
     $upscope $end
     $scope module adder_chain[1] $end
      $scope module fa $end
       $var wire 1 V a_i $end
       $var wire 1 0 b_i $end
       $var wire 1 1 c_i $end
       $var wire 1 2 sum_o $end
       $var wire 1 W c_o $end
      $upscope $end
     $upscope $end
     $scope module adder_chain[2] $end
      $scope module fa $end
       $var wire 1 X a_i $end
       $var wire 1 3 b_i $end
       $var wire 1 4 c_i $end
       $var wire 1 5 sum_o $end
       $var wire 1 Y c_o $end
      $upscope $end
     $upscope $end
     $scope module adder_chain[3] $end
      $scope module fa $end
       $var wire 1 Z a_i $end
       $var wire 1 6 b_i $end
       $var wire 1 7 c_i $end
       $var wire 1 8 sum_o $end
       $var wire 1 [ c_o $end
      $upscope $end
     $upscope $end
     $scope module adder_chain[4] $end
      $scope module fa $end
       $var wire 1 \ a_i $end
       $var wire 1 9 b_i $end
       $var wire 1 : c_i $end
       $var wire 1 ; sum_o $end
       $var wire 1 ] c_o $end
      $upscope $end
     $upscope $end
     $scope module adder_chain[5] $end
      $scope module fa $end
       $var wire 1 ^ a_i $end
       $var wire 1 < b_i $end
       $var wire 1 = c_i $end
       $var wire 1 > sum_o $end
       $var wire 1 _ c_o $end
      $upscope $end
     $upscope $end
     $scope module adder_chain[6] $end
      $scope module fa $end
       $var wire 1 ` a_i $end
       $var wire 1 ? b_i $end
       $var wire 1 @ c_i $end
       $var wire 1 A sum_o $end
       $var wire 1 a c_o $end
      $upscope $end
     $upscope $end
     $scope module adder_chain[7] $end
      $scope module fa $end
       $var wire 1 b a_i $end
       $var wire 1 B b_i $end
       $var wire 1 C c_i $end
       $var wire 1 D sum_o $end
       $var wire 1 c c_o $end
      $upscope $end
     $upscope $end
    $upscope $end
    $scope module output_mux $end
     $var wire 32 d BitWidth [31:0] $end
     $var wire 32 d N [31:0] $end
     $var wire 32 e SelWidth [31:0] $end
     $var wire 8 E d_i[0] [7:0] $end
     $var wire 8 F d_i[1] [7:0] $end
     $var wire 8 G d_i[2] [7:0] $end
     $var wire 8 H d_i[3] [7:0] $end
     $var wire 8 I d_i[4] [7:0] $end
     $var wire 8 J d_i[5] [7:0] $end
     $var wire 8 K d_i[6] [7:0] $end
     $var wire 8 L d_i[7] [7:0] $end
     $var wire 3 O sel_i [2:0] $end
     $var wire 8 P d_o [7:0] $end
    $upscope $end
   $upscope $end
  $upscope $end
 $upscope $end
$enddefinitions $end


#10
0#
1$
0%
b11101100 &
b11110110 '
b11110110 (
b00000000 )
b11110110 *
1+
b11110110 ,
b11110110 -
0.
0/
10
01
02
13
14
15
06
17
18
19
0:
0;
1<
1=
1>
1?
1@
1A
1B
1C
1D
b11101100 E
b11101100 F
b11110110 G
b11110110 H
b00000000 I
b11101100 J
b11110110 K
b11110110 L
b11110110 M
b11110110 N
b000 O
b11101100 P
b010 Q
0R
b111101100 S
0T
0U
1V
1W
1X
1Y
0Z
0[
1\
1]
1^
1_
1`
1a
1b
1c
b00000000000000000000000000001000 d
b00000000000000000000000000000011 e
#20
b11101101 &
b11110111 (
b00000001 )
b11110111 *
b11110111 -
1.
1/
b11101101 E
b11101101 F
b11110111 H
b00000001 I
b11101101 J
b11110111 L
b11110111 N
b11101101 P
#30
b11101110 &
b11110000 '
b11111110 (
b00001110 )
b11111000 *
b11110000 ,
b11111110 -
0.
0/
00
12
03
04
16
07
b11101110 E
b11101110 F
b11110000 G
b11111110 H
b00001110 I
b11101110 J
b11111000 L
b11111000 N
b11101110 P
b111100000 S
0W
0Y
#40
b11101111 &
b11111111 (
b00001111 )
b11111001 *
b11111111 -
1.
1/
b11101111 E
b11101111 F
b11111111 H
b00001111 I
b11101111 J
b11111001 L
b11111001 N
b11101111 P
#50
b11110000 &
b11110010 '
b11111110 (
b00001100 )
b11111010 *
b11110010 ,
b11111110 -
0.
0/
10
02
14
05
17
08
1:
1;
b11110000 E
b11110000 F
b11110010 G
b11111110 H
b00001100 I
b11110000 J
b11111010 L
b11111010 N
b11110000 P
b111111100 S
1W
1Y
1[
#60
b11110001 &
b11111111 (
b00001101 )
b11111011 *
b11111111 -
1.
1/
b11110001 E
b11110001 F
b11111111 H
b00001101 I
b11110001 J
b11111011 L
b11111011 N
b11110001 P
#70
b11110010 &
b11110100 '
b11111110 (
b00001010 )
b11111100 *
b11110100 ,
b11111110 -
0.
0/
00
12
13
04
b11110010 E
b11110010 F
b11110100 G
b11111110 H
b00001010 I
b11110010 J
b11111100 L
b11111100 N
b11110010 P
b111111000 S
0W
#80
b11110011 &
b11111111 (
b00001011 )
b11111101 *
b11111111 -
1.
1/
b11110011 E
b11110011 F
b11111111 H
b00001011 I
b11110011 J
b11111101 L
b11111101 N
b11110011 P
#90
b11110100 &
b11110110 '
b11111110 (
b00001000 )
b11111110 *
b11110110 ,
b11111110 -
0.
0/
10
02
14
15
b11110100 E
b11110100 F
b11110110 G
b11111110 H
b00001000 I
b11110100 J
b11111110 L
b11111110 N
b11110100 P
b111111100 S
1W
#100
b11110101 &
b11111111 (
b00001001 )
b11111111 *
b11111111 -
1.
1/
b11110101 E
b11110101 F
b11111111 H
b00001001 I
b11110101 J
b11111111 L
b11111111 N
b11110101 P
#110
b11110110 &
b00000000 '
b11110110 (
b11110110 )
b00000000 *
0+
b00000000 ,
b11110110 -
0.
0/
00
12
03
04
06
07
09
0:
0<
0=
0?
0@
0B
0C
b11110110 E
b11110110 F
b00000000 G
b11110110 H
b11110110 I
b11110110 J
b00000000 L
b00000000 N
b11110110 P
b000000000 S
0W
0Y
0[
0]
0_
0a
0c
#120
b11110111 &
b11110111 (
b11110111 )
b00000001 *
b11110111 -
1.
1/
b11110111 E
b11110111 F
b11110111 H
b11110111 I
b11110111 J
b00000001 L
b00000001 N
b11110111 P
#130
b11111000 &
b00000010 '
b11110110 (
b11110100 )
b00000010 *
b00000010 ,
b11110110 -
0.
0/
10
02
14
05
17
18
b11111000 E
b11111000 F
b00000010 G
b11110110 H
b11110100 I
b11111000 J
b00000010 L
b00000010 N
b11111000 P
b000001100 S
1W
1Y
#140
b11111001 &
b11110111 (
b11110101 )
b00000011 *
b11110111 -
1.
1/
b11111001 E
b11111001 F
b11110111 H
b11110101 I
b11111001 J
b00000011 L
b00000011 N
b11111001 P
#150
b11111010 &
b00000100 '
b11110110 (
b11110010 )
b00000100 *
b00000100 ,
b11110110 -
0.
0/
00
12
13
04
b11111010 E
b11111010 F
b00000100 G
b11110110 H
b11110010 I
b11111010 J
b00000100 L
b00000100 N
b11111010 P
b000001000 S
0W
#160
b11111011 &
b11110111 (
b11110011 )
b00000101 *
b11110111 -
1.
1/
b11111011 E
b11111011 F
b11110111 H
b11110011 I
b11111011 J
b00000101 L
b00000101 N
b11111011 P
#170
b11111100 &
b00000110 '
b11110110 (
b11110000 )
b00000110 *
b00000110 ,
b11110110 -
0.
0/
10
02
14
15
b11111100 E
b11111100 F
b00000110 G
b11110110 H
b11110000 I
b11111100 J
b00000110 L
b00000110 N
b11111100 P
b000001100 S
1W
#180
b11111101 &
b11110111 (
b11110001 )
b00000111 *
b11110111 -
1.
1/
b11111101 E
b11111101 F
b11110111 H
b11110001 I
b11111101 J
b00000111 L
b00000111 N
b11111101 P
#190
b11111110 &
b00000000 '
b11111110 (
b11111110 )
b00001000 *
b00000000 ,
b11111110 -
0.
0/
00
12
03
04
16
07
b11111110 E
b11111110 F
b00000000 G
b11111110 H
b11111110 I
b11111110 J
b00001000 L
b00001000 N
b11111110 P
b000000000 S
0W
0Y
#200
b11111111 &
b11111111 (
b11111111 )
b00001001 *
b11111111 -
1.
1/
b11111111 E
b11111111 F
b11111111 H
b11111111 I
b11111111 J
b00001001 L
b00001001 N
b11111111 P
#210
b11101101 &
b11110110 '
b11110111 (
b00000001 )
b11110110 *
1+
b11110110 ,
b11110111 -
0.
10
02
13
14
06
17
19
0;
1<
1=
1?
1@
1B
1C
b11101101 E
b11101101 F
b11110110 G
b11110111 H
b00000001 I
b11101101 J
b11110111 K
b11110110 L
b11110111 M
b11110110 N
b11101101 P
b111101100 S
1T
1W
1Y
1]
1_
1a
1c
#220
b11101110 &
b11110111 '
b00000000 )
b11110111 *
b11110111 ,
1.
0/
11
12
b11101110 E
b11101110 F
b11110111 G
b00000000 I
b11101110 J
b11110111 L
b11110111 N
b11101110 P
b111101110 S
1U
#230
b11101111 &
b11110000 '
b11111111 (
b00001111 )
b11111000 *
b11110000 ,
b11111111 -
0.
1/
00
01
03
04
16
07
b11101111 E
b11101111 F
b11110000 G
b11111111 H
b00001111 I
b11101111 J
b11111000 L
b11111000 N
b11101111 P
b111100000 S
0U
0W
0Y
#240
b11110000 &
b11110001 '
b00001110 )
b11111001 *
b11110001 ,
1.
0/
11
02
14
05
17
08
1:
1;
b11110000 E
b11110000 F
b11110001 G
b00001110 I
b11110000 J
b11111001 L
b11111001 N
b11110000 P
b111111110 S
1U
1W
1Y
1[
#250
b11110001 &
b11110010 '
b00001101 )
b11111010 *
b11110010 ,
0.
1/
10
01
b11110001 E
b11110001 F
b11110010 G
b00001101 I
b11110001 J
b11111010 L
b11111010 N
b11110001 P
b111111100 S
0U
#260
b11110010 &
b11110011 '
b00001100 )
b11111011 *
b11110011 ,
1.
0/
11
12
b11110010 E
b11110010 F
b11110011 G
b00001100 I
b11110010 J
b11111011 L
b11111011 N
b11110010 P
b111111110 S
1U
#270
b11110011 &
b11110100 '
b00001011 )
b11111100 *
b11110100 ,
0.
1/
00
01
13
04
b11110011 E
b11110011 F
b11110100 G
b00001011 I
b11110011 J
b11111100 L
b11111100 N
b11110011 P
b111111000 S
0U
0W
#280
b11110100 &
b11110101 '
b00001010 )
b11111101 *
b11110101 ,
1.
0/
11
02
14
15
b11110100 E
b11110100 F
b11110101 G
b00001010 I
b11110100 J
b11111101 L
b11111101 N
b11110100 P
b111111110 S
1U
1W
#290
b11110101 &
b11110110 '
b00001001 )
b11111110 *
b11110110 ,
0.
1/
10
01
b11110101 E
b11110101 F
b11110110 G
b00001001 I
b11110101 J
b11111110 L
b11111110 N
b11110101 P
b111111100 S
0U
#300
b11110110 &
b11110111 '
b00001000 )
b11111111 *
b11110111 ,
1.
0/
11
12
b11110110 E
b11110110 F
b11110111 G
b00001000 I
b11110110 J
b11111111 L
b11111111 N
b11110110 P
b111111110 S
1U
#310
b11110111 &
b00000000 '
b11110111 (
b11110111 )
b00000000 *
0+
b00000000 ,
b11110111 -
0.
1/
00
01
03
04
06
07
09
0:
0<
0=
0?
0@
0B
0C
b11110111 E
b11110111 F
b00000000 G
b11110111 H
b11110111 I
b11110111 J
b00000000 L
b00000000 N
b11110111 P
b000000000 S
0U
0W
0Y
0[
0]
0_
0a
0c
#320
b11111000 &
b00000001 '
b11110110 )
b00000001 *
b00000001 ,
1.
0/
11
02
14
05
17
18
b11111000 E
b11111000 F
b00000001 G
b11110110 I
b11111000 J
b00000001 L
b00000001 N
b11111000 P
b000001110 S
1U
1W
1Y
#330
b11111001 &
b00000010 '
b11110101 )
b00000010 *
b00000010 ,
0.
1/
10
01
b11111001 E
b11111001 F
b00000010 G
b11110101 I
b11111001 J
b00000010 L
b00000010 N
b11111001 P
b000001100 S
0U
#340
b11111010 &
b00000011 '
b11110100 )
b00000011 *
b00000011 ,
1.
0/
11
12
b11111010 E
b11111010 F
b00000011 G
b11110100 I
b11111010 J
b00000011 L
b00000011 N
b11111010 P
b000001110 S
1U
#350
b11111011 &
b00000100 '
b11110011 )
b00000100 *
b00000100 ,
0.
1/
00
01
13
04
b11111011 E
b11111011 F
b00000100 G
b11110011 I
b11111011 J
b00000100 L
b00000100 N
b11111011 P
b000001000 S
0U
0W
#360
b11111100 &
b00000101 '
b11110010 )
b00000101 *
b00000101 ,
1.
0/
11
02
14
15
b11111100 E
b11111100 F
b00000101 G
b11110010 I
b11111100 J
b00000101 L
b00000101 N
b11111100 P
b000001110 S
1U
1W
#370
b11111101 &
b00000110 '
b11110001 )
b00000110 *
b00000110 ,
0.
1/
10
01
b11111101 E
b11111101 F
b00000110 G
b11110001 I
b11111101 J
b00000110 L
b00000110 N
b11111101 P
b000001100 S
0U
#380
b11111110 &
b00000111 '
b11110000 )
b00000111 *
b00000111 ,
1.
0/
11
12
b11111110 E
b11111110 F
b00000111 G
b11110000 I
b11111110 J
b00000111 L
b00000111 N
b11111110 P
b000001110 S
1U
#390
b11111111 &
b00000000 '
b11111111 (
b11111111 )
b00001000 *
b00000000 ,
b11111111 -
0.
1/
00
01
03
04
16
07
b11111111 E
b11111111 F
b00000000 G
b11111111 H
b11111111 I
b11111111 J
b00001000 L
b00001000 N
b11111111 P
b000000000 S
0U
0W
0Y
#400
0$
1%
b00000000 &
b00000001 '
b11111110 )
b00001001 *
1+
b00000001 ,
1.
0/
11
02
14
05
17
08
1:
0;
1=
0>
1@
0A
1C
0D
b00000000 E
b00000000 F
b00000001 G
b11111110 I
b00000000 J
b00001001 L
b00001001 N
b00000000 P
b001 Q
b111111110 S
1U
1W
1Y
1[
1]
1_
1a
1c
#410
1$
0%
b11101110 &
b11110000 '
b11111110 (
b00001110 )
b11110110 *
b11110000 ,
b11111110 -
0.
10
01
12
13
04
15
06
07
18
19
0:
1<
1>
1?
1A
1B
1D
b11101110 E
b11101110 F
b11110000 G
b11111110 H
b00001110 I
b11101110 J
b11111000 K
b11110110 L
b11111000 M
b11110110 N
b11101110 P
b010 Q
b111100000 S
0T
0U
0V
0W
0X
0Y
1Z
0[
#420
b11101111 &
b11111111 (
b00001111 )
b11110111 *
b11111111 -
1.
1/
b11101111 E
b11101111 F
b11111111 H
b00001111 I
b11101111 J
b11110111 L
b11110111 N
b11101111 P
#430
b11110000 &
b11111000 '
b11111000 (
b00000000 )
b11111000 *
b11111000 ,
b11111000 -
0.
0/
00
02
03
05
16
08
1:
1;
b11110000 E
b11110000 F
b11111000 G
b11111000 H
b00000000 I
b11110000 J
b11111000 L
b11111000 N
b11110000 P
b111110000 S
1[
#440
b11110001 &
b11111001 (
b00000001 )
b11111001 *
b11111001 -
1.
1/
b11110001 E
b11110001 F
b11111001 H
b00000001 I
b11110001 J
b11111001 L
b11111001 N
b11110001 P
#450
b11110010 &
b11111010 (
b00000010 )
b11111010 *
b11111010 -
0.
0/
10
12
b11110010 E
b11110010 F
b11111010 H
b00000010 I
b11110010 J
b11111010 L
b11111010 N
b11110010 P
#460
b11110011 &
b11111011 (
b00000011 )
b11111011 *
b11111011 -
1.
1/
b11110011 E
b11110011 F
b11111011 H
b00000011 I
b11110011 J
b11111011 L
b11111011 N
b11110011 P
#470
b11110100 &
b11111100 (
b00000100 )
b11111100 *
b11111100 -
0.
0/
00
02
13
15
b11110100 E
b11110100 F
b11111100 H
b00000100 I
b11110100 J
b11111100 L
b11111100 N
b11110100 P
#480
b11110101 &
b11111101 (
b00000101 )
b11111101 *
b11111101 -
1.
1/
b11110101 E
b11110101 F
b11111101 H
b00000101 I
b11110101 J
b11111101 L
b11111101 N
b11110101 P
#490
b11110110 &
b11111110 (
b00000110 )
b11111110 *
b11111110 -
0.
0/
10
12
b11110110 E
b11110110 F
b11111110 H
b00000110 I
b11110110 J
b11111110 L
b11111110 N
b11110110 P
#500
b11110111 &
b11111111 (
b00000111 )
b11111111 *
b11111111 -
1.
1/
b11110111 E
b11110111 F
b11111111 H
b00000111 I
b11110111 J
b11111111 L
b11111111 N
b11110111 P
#510
b11111000 &
b00000000 '
b11111000 (
b11111000 )
b00000000 *
0+
b00000000 ,
b11111000 -
0.
0/
00
02
03
05
06
18
09
0:
0<
0=
0?
0@
0B
0C
b11111000 E
b11111000 F
b00000000 G
b11111000 H
b11111000 I
b11111000 J
b00000000 L
b00000000 N
b11111000 P
b000000000 S
0[
0]
0_
0a
0c
#520
b11111001 &
b11111001 (
b11111001 )
b00000001 *
b11111001 -
1.
1/
b11111001 E
b11111001 F
b11111001 H
b11111001 I
b11111001 J
b00000001 L
b00000001 N
b11111001 P
#530
b11111010 &
b11111010 (
b11111010 )
b00000010 *
b11111010 -
0.
0/
10
12
b11111010 E
b11111010 F
b11111010 H
b11111010 I
b11111010 J
b00000010 L
b00000010 N
b11111010 P
#540
b11111011 &
b11111011 (
b11111011 )
b00000011 *
b11111011 -
1.
1/
b11111011 E
b11111011 F
b11111011 H
b11111011 I
b11111011 J
b00000011 L
b00000011 N
b11111011 P
#550
b11111100 &
b11111100 (
b11111100 )
b00000100 *
b11111100 -
0.
0/
00
02
13
15
b11111100 E
b11111100 F
b11111100 H
b11111100 I
b11111100 J
b00000100 L
b00000100 N
b11111100 P
#560
b11111101 &
b11111101 (
b11111101 )
b00000101 *
b11111101 -
1.
1/
b11111101 E
b11111101 F
b11111101 H
b11111101 I
b11111101 J
b00000101 L
b00000101 N
b11111101 P
#570
b11111110 &
b11111110 (
b11111110 )
b00000110 *
b11111110 -
0.
0/
10
12
b11111110 E
b11111110 F
b11111110 H
b11111110 I
b11111110 J
b00000110 L
b00000110 N
b11111110 P
#580
b11111111 &
b11111111 (
b11111111 )
b00000111 *
b11111111 -
1.
1/
b11111111 E
b11111111 F
b11111111 H
b11111111 I
b11111111 J
b00000111 L
b00000111 N
b11111111 P
#590
0$
1%
b00000000 &
b00001000 '
b11111000 (
b11110000 )
b00001000 *
1+
b00001000 ,
b11111000 -
0.
0/
00
02
03
05
16
08
1:
0;
1=
0>
1@
0A
1C
0D
b00000000 E
b00000000 F
b00001000 G
b11111000 H
b11110000 I
b00000000 J
b00001000 L
b00001000 N
b00000000 P
b001 Q
b111110000 S
1[
1]
1_
1a
1c
#600
0%
b00000001 &
b11111001 (
b11110001 )
b00001001 *
b11111001 -
1.
1/
b00000001 E
b00000001 F
b11111001 H
b11110001 I
b00000001 J
b00001001 L
b00001001 N
b00000001 P
b000 Q
#610
1$
b11101111 &
b11110000 '
b11111111 (
b00001111 )
b11110110 *
b11110000 ,
b11111111 -
0.
10
12
13
15
06
18
19
0:
1<
1>
1?
1A
1B
1D
b11101111 E
b11101111 F
b11110000 G
b11111111 H
b00001111 I
b11101111 J
b11111001 K
b11110110 L
b11111001 M
b11110110 N
b11101111 P
b010 Q
b111100000 S
1T
0[
#620
b11110000 &
b11110001 '
b00001110 )
b11110111 *
b11110001 ,
1.
0/
11
02
14
05
17
08
1:
1;
b11110000 E
b11110000 F
b11110001 G
b00001110 I
b11110000 J
b11110111 L
b11110111 N
b11110000 P
b111111110 S
1U
1W
1Y
1[
#630
b11110001 &
b11111000 '
b11111001 (
b00000001 )
b11111000 *
b11111000 ,
b11111001 -
0.
1/
00
01
03
04
16
07
b11110001 E
b11110001 F
b11111000 G
b11111001 H
b00000001 I
b11110001 J
b11111000 L
b11111000 N
b11110001 P
b111110000 S
0U
0W
0Y
#640
b11110010 &
b11111001 '
b00000000 )
b11111001 *
b11111001 ,
1.
0/
11
12
b11110010 E
b11110010 F
b11111001 G
b00000000 I
b11110010 J
b11111001 L
b11111001 N
b11110010 P
b111110010 S
1U
#650
b11110011 &
b11111000 '
b11111011 (
b00000011 )
b11111010 *
b11111000 ,
b11111011 -
0.
1/
10
01
b11110011 E
b11110011 F
b11111000 G
b11111011 H
b00000011 I
b11110011 J
b11111010 L
b11111010 N
b11110011 P
b111110000 S
0U
#660
b11110100 &
b11111001 '
b00000010 )
b11111011 *
b11111001 ,
1.
0/
11
02
14
15
b11110100 E
b11110100 F
b11111001 G
b00000010 I
b11110100 J
b11111011 L
b11111011 N
b11110100 P
b111110110 S
1U
1W
#670
b11110101 &
b11111000 '
b11111101 (
b00000101 )
b11111100 *
b11111000 ,
b11111101 -
0.
1/
00
01
13
04
b11110101 E
b11110101 F
b11111000 G
b11111101 H
b00000101 I
b11110101 J
b11111100 L
b11111100 N
b11110101 P
b111110000 S
0U
0W
#680
b11110110 &
b11111001 '
b00000100 )
b11111101 *
b11111001 ,
1.
0/
11
12
b11110110 E
b11110110 F
b11111001 G
b00000100 I
b11110110 J
b11111101 L
b11111101 N
b11110110 P
b111110010 S
1U
#690
b11110111 &
b11111000 '
b11111111 (
b00000111 )
b11111110 *
b11111000 ,
b11111111 -
0.
1/
10
01
b11110111 E
b11110111 F
b11111000 G
b11111111 H
b00000111 I
b11110111 J
b11111110 L
b11111110 N
b11110111 P
b111110000 S
0U
#700
b11111000 &
b11111001 '
b00000110 )
b11111111 *
b11111001 ,
1.
0/
11
02
14
05
17
18
b11111000 E
b11111000 F
b11111001 G
b00000110 I
b11111000 J
b11111111 L
b11111111 N
b11111000 P
b111111110 S
1U
1W
1Y
#710
b11111001 &
b00000000 '
b11111001 (
b11111001 )
b00000000 *
0+
b00000000 ,
b11111001 -
0.
1/
00
01
03
04
06
07
09
0:
0<
0=
0?
0@
0B
0C
b11111001 E
b11111001 F
b00000000 G
b11111001 H
b11111001 I
b11111001 J
b00000000 L
b00000000 N
b11111001 P
b000000000 S
0U
0W
0Y
0[
0]
0_
0a
0c
#720
b11111010 &
b00000001 '
b11111000 )
b00000001 *
b00000001 ,
1.
0/
11
12
b11111010 E
b11111010 F
b00000001 G
b11111000 I
b11111010 J
b00000001 L
b00000001 N
b11111010 P
b000000010 S
1U
#730
b11111011 &
b00000000 '
b11111011 (
b11111011 )
b00000010 *
b00000000 ,
b11111011 -
0.
1/
10
01
b11111011 E
b11111011 F
b00000000 G
b11111011 H
b11111011 I
b11111011 J
b00000010 L
b00000010 N
b11111011 P
b000000000 S
0U
#740
b11111100 &
b00000001 '
b11111010 )
b00000011 *
b00000001 ,
1.
0/
11
02
14
15
b11111100 E
b11111100 F
b00000001 G
b11111010 I
b11111100 J
b00000011 L
b00000011 N
b11111100 P
b000000110 S
1U
1W
